opensourceleg/__init__.py
opensourceleg/actuators/README.md
opensourceleg/actuators/__init__.py
opensourceleg/actuators/base.py
opensourceleg/actuators/decorators.py
opensourceleg/actuators/dephy.py
opensourceleg/actuators/moteus.py
opensourceleg/actuators/tmotor.py
opensourceleg/actuators/images/Class Diagram Base Lib.svg
opensourceleg/common/__init__.py
opensourceleg/common/offline.py
opensourceleg/control/__init__.py
opensourceleg/control/compiled.py
opensourceleg/control/fsm.py
opensourceleg/extras/__init__.py
opensourceleg/extras/benchmarks/__init__.py
opensourceleg/extras/benchmarks/decorators.py
opensourceleg/extras/benchmarks/threads.py
opensourceleg/extras/collections/__init__.py
opensourceleg/extras/collections/validators.py
opensourceleg/extras/safety/README.md
opensourceleg/extras/safety/__init__.py
opensourceleg/extras/safety/safety.py
opensourceleg/generators/__init__.py
opensourceleg/generators/base.py
opensourceleg/generators/expression_evaluator.py
opensourceleg/generators/signal_generators.py
opensourceleg/logging/__init__.py
opensourceleg/logging/decorators.py
opensourceleg/logging/exceptions.py
opensourceleg/logging/logger.py
opensourceleg/math/__init__.py
opensourceleg/math/math.py
opensourceleg/robots/__init__.py
opensourceleg/robots/base.py
opensourceleg/robots/osl.py
opensourceleg/sensors/README.md
opensourceleg/sensors/__init__.py
opensourceleg/sensors/adc.py
opensourceleg/sensors/base.py
opensourceleg/sensors/encoder.py
opensourceleg/sensors/imu.py
opensourceleg/sensors/loadcell.py
opensourceleg/utilities/__init__.py
opensourceleg/utilities/profile.py
opensourceleg/utilities/softrealtimeloop.py
opensourceleg/utilities/units.py
opensourceleg-3.4.2.dist-info/METADATA
opensourceleg-3.4.2.dist-info/WHEEL
opensourceleg-3.4.2.dist-info/licenses/LICENSE
opensourceleg-3.4.2.dist-info/RECORD
