Metadata-Version: 2.4
Name: opensourceleg
Version: 3.4.2
Summary: An open-source SDK for developing and testing algorithms on commonly used robotic hardware.
Project-URL: Repository, https://github.com/neurobionics/opensourceleg
Project-URL: Documentation, https://neurobionics.github.io/opensourceleg/
Author-email: Open-Source Leg <opensourceleg@gmail.com>
License-File: LICENSE
Requires-Python: <4.0,>=3.11
Requires-Dist: numpy<2,>=1.24.3
Requires-Dist: pandas<3,>=2.2.3
Provides-Extra: bno055
Requires-Dist: adafruit-circuitpython-bno055<6,>=5.4.13; (sys_platform == 'linux' and platform_machine == 'aarch64') and extra == 'bno055'
Requires-Dist: adafruit-circuitpython-lis3dh<6,>=5.2.2; (sys_platform == 'linux' and platform_machine == 'aarch64') and extra == 'bno055'
Requires-Dist: board~=1.0; extra == 'bno055'
Provides-Extra: communication
Requires-Dist: smbus2>=0.4.2; extra == 'communication'
Requires-Dist: spidev>=3.7; (sys_platform == 'linux') and extra == 'communication'
Provides-Extra: dephy
Requires-Dist: flexsea; extra == 'dephy'
Provides-Extra: messaging
Requires-Dist: grpcio-tools<2,>=1.65.5; extra == 'messaging'
Requires-Dist: grpcio<2,>=1.65.5; extra == 'messaging'
Requires-Dist: types-protobuf<5,>=4.21.0; extra == 'messaging'
Provides-Extra: moteus
Requires-Dist: moteus-pi3hat<0.4,>=0.3.29; (sys_platform == 'linux' and platform_machine == 'aarch64') and extra == 'moteus'
Requires-Dist: moteus<0.4,>=0.3.72; extra == 'moteus'
